{
  "name": "t:sections.header.name",
  "type": "header",
  "sections": {
    "announcement-bar": {
      "type": "announcement-bar",
      "blocks": {
        "announcement-bar-0": {
          "type": "announcement",
          "settings": {
            "text": "Handmade in Berlin",
            "link": ""
          }
        },
        "233074dc-611e-4815-968e-7ab015d25288": {
          "type": "announcement",
          "disabled": true,
          "settings": {
            "text": "Neues Design",
            "link": ""
          }
        },
        "6b1df875-7d43-4b20-8e8f-621f0c991c03": {
          "type": "announcement",
          "disabled": true,
          "settings": {
            "text": "Versand nach DE kostenlos ab 100 €",
            "link": "shopify:\/\/pages\/versandkosten"
          }
        }
      },
      "block_order": [
        "announcement-bar-0",
        "233074dc-611e-4815-968e-7ab015d25288",
        "6b1df875-7d43-4b20-8e8f-621f0c991c03"
      ],
      "settings": {
        "color_scheme": "scheme-c986199f-beb4-486d-8120-d3e8779b7b9e",
        "show_line_separator": true,
        "auto_rotate": true,
        "change_slides_speed": 5
      }
    },
    "header": {
      "type": "header",
      "settings": {
        "logo_position": "middle-left",
        "menu": "main-menu",
        "menu_type_desktop": "mega",
        "sticky_header_type": "on-scroll-up",
        "show_line_separator": true,
        "color_scheme": "scheme-5f541abf-2222-4580-9242-293f60c35b1b",
        "enable_country_selector": false,
        "enable_language_selector": true,
        "mobile_logo_position": "center",
        "margin_bottom": 0,
        "padding_top": 20,
        "padding_bottom": 20
      }
    }
  },
  "order": [
    "announcement-bar",
    "header"
  ]
}
