{
  "sections": {
    "main": {
      "type": "main-product",
      "blocks": {
        "vendor": {
          "type": "text",
          "settings": {
            "text": "{{ product.vendor }}",
            "text_style": "uppercase"
          }
        },
        "title": {
          "type": "title",
          "settings": {
          }
        },
        "aab53c8d-9763-4b25-8787-a1162ec46c69": {
          "type": "text",
          "settings": {
            "text": "{{ product.metafields.custom.size_alc.value }}",
            "text_style": "subtitle"
          }
        },
        "caption": {
          "type": "text",
          "settings": {
            "text": "{{ product.metafields.descriptors.subtitle.value }}",
            "text_style": "subtitle"
          }
        },
        "price": {
          "type": "price",
          "settings": {
          }
        },
        "variant_picker": {
          "type": "variant_picker",
          "settings": {
            "picker_type": "button"
          }
        },
        "quantity_selector": {
          "type": "quantity_selector",
          "settings": {
          }
        },
        "buy_buttons": {
          "type": "buy_buttons",
          "settings": {
            "show_dynamic_checkout": true,
            "show_gift_card_recipient": true
          }
        },
        "description": {
          "type": "description",
          "settings": {
          }
        },
        "collapsible-row-1": {
          "type": "collapsible_tab",
          "settings": {
            "heading": "Handgemacht in Berlin",
            "icon": "heart",
            "content": "<p>Gentle Gin wird mit Liebe und in kleinen Chargen von Hand produziert und abgefüllt.<\/p>",
            "page": "versandkosten"
          }
        },
        "37ec0522-ee9c-4436-a63b-00e9290c104b": {
          "type": "collapsible_tab",
          "settings": {
            "heading": "DHL Versand",
            "icon": "truck",
            "content": "",
            "page": "versandkosten"
          }
        },
        "a68fccd4-07e0-4043-b9dd-c152b0617bad": {
          "type": "collapsible_tab",
          "settings": {
            "heading": "Schnell & sicher zahlen",
            "icon": "lock",
            "content": "<p>Wir unterstützen <strong>alle gängigen Zahlungsanbieter<\/strong> über unser <br\/>verschlüsseltes Zahlungsportal. Darunter auch <strong>Raten- und Rechnungskauf<\/strong> <br\/>über Klarna.<\/p>",
            "page": ""
          }
        },
        "share": {
          "type": "share",
          "settings": {
            "share_label": "Share"
          }
        }
      },
      "block_order": [
        "vendor",
        "title",
        "aab53c8d-9763-4b25-8787-a1162ec46c69",
        "caption",
        "price",
        "variant_picker",
        "quantity_selector",
        "buy_buttons",
        "description",
        "collapsible-row-1",
        "37ec0522-ee9c-4436-a63b-00e9290c104b",
        "a68fccd4-07e0-4043-b9dd-c152b0617bad",
        "share"
      ],
      "settings": {
        "enable_sticky_info": true,
        "media_size": "large",
        "constrain_to_viewport": true,
        "media_fit": "contain",
        "gallery_layout": "thumbnail_slider",
        "media_position": "left",
        "image_zoom": "hover",
        "mobile_thumbnails": "hide",
        "hide_variants": true,
        "enable_video_looping": false,
        "padding_top": 36,
        "padding_bottom": 12
      }
    },
    "4315c828-724c-4210-9c82-6797dbd2bf5d": {
      "type": "image-with-text",
      "blocks": {
        "e87671a0-7557-4830-b1e8-becbc68c0b11": {
          "type": "caption",
          "settings": {
            "caption": "Gentle Gin Tea Blue",
            "text_style": "caption-with-letter-spacing",
            "text_size": "medium"
          }
        },
        "c998a453-70fb-4db6-ad9c-01137aa4c0be": {
          "type": "heading",
          "settings": {
            "heading": "Dein blaues Wunder",
            "heading_size": "h1"
          }
        },
        "0dceb4f1-bf93-4580-a65e-cb41b49db3c5": {
          "type": "text",
          "settings": {
            "text": "<p>Bist du bereit für ein Getränk, das nicht nur deinen Gaumen, sondern auch deine Augen betört? Dann triff unseren Gentle Gin Tea Blue, ein Gin-Erlebnis, das sich vor deinen Augen entfaltet.<\/p><p>Tea Blue ist ein magischer Trank in strahlendem Saphirblau. Seine faszinierende Farbe verdankt er dem exotischen indonesischen Schmetterlingstee, auch bekannt als \"blaue Klitorie\". Aber die Magie endet hier nicht. Gib etwas Tonic oder Säure hinzu, und schau zu, wie sich die blaue Farbe in ein verträumtes Violett verwandelt. Es ist ein zauberhaftes Schauspiel, eine Farbexplosion, die jeden Cocktailabend in ein unvergessliches Erlebnis verwandelt.<\/p>",
            "text_style": "body"
          }
        }
      },
      "block_order": [
        "e87671a0-7557-4830-b1e8-becbc68c0b11",
        "c998a453-70fb-4db6-ad9c-01137aa4c0be",
        "0dceb4f1-bf93-4580-a65e-cb41b49db3c5"
      ],
      "settings": {
        "image": "shopify:\/\/shop_images\/A_tall_highball_glass_filled_halfway_with_the_sap_09bd0baf-5a1e-40c5-921e-586738f9f63b.png",
        "height": "small",
        "desktop_image_width": "small",
        "layout": "text_first",
        "desktop_content_position": "bottom",
        "desktop_content_alignment": "left",
        "content_layout": "overlap",
        "color_scheme": "inverse",
        "image_behavior": "ambient",
        "mobile_content_alignment": "left",
        "padding_top": 36,
        "padding_bottom": 32
      }
    },
    "f22dd3f3-92ca-453d-b11e-673b4447da27": {
      "type": "rich-text",
      "blocks": {
        "6da49d3b-6e4e-4a00-987d-54e6e4cfcde6": {
          "type": "text",
          "settings": {
            "text": "<p>Mit seinem sanft süßen Geschmack und dem dezenten Wacholderaroma ist er ein Hochgenuss für den Gaumen. Er ist ein perfektes Gleichgewicht zwischen Zartheit und Stärke, zwischen Süße und Bitterkeit. Mit jedem Schluck, mit jedem Farbwechsel entführt er dich in eine Welt der Wunder und Fantasie.<\/p>"
          }
        }
      },
      "block_order": [
        "6da49d3b-6e4e-4a00-987d-54e6e4cfcde6"
      ],
      "custom_css": [
        "p {font-size: 2rem; font-weight: bold;}"
      ],
      "settings": {
        "desktop_content_position": "center",
        "content_alignment": "center",
        "color_scheme": "scheme-c986199f-beb4-486d-8120-d3e8779b7b9e",
        "full_width": true,
        "padding_top": 8,
        "padding_bottom": 12
      }
    },
    "6967ccec-2575-44cc-8175-79ab53e008c4": {
      "type": "image-with-text",
      "blocks": {
        "8f6705b9-a5fc-49b3-87b9-f8fcde0f8a07": {
          "type": "heading",
          "settings": {
            "heading": "Verzaubere deine Gäste",
            "heading_size": "h2"
          }
        },
        "4d2529eb-841c-4cb4-9a60-ebbc15bb507e": {
          "type": "text",
          "settings": {
            "text": "<p>Lass dich und deine Freunde verzaubern von der Magie des Gentle Gin Tea Blue. Probiere ihn pur, auf Eis oder in einem verführerischen Cocktail. Genieße das Spektakel, wie er seine Farbe verändert, und tauche ein in ein Geschmackserlebnis, das du so noch nie erlebt hast. Willkommen in der Gentle Gin Welt!<\/p>",
            "text_style": "body"
          }
        }
      },
      "block_order": [
        "8f6705b9-a5fc-49b3-87b9-f8fcde0f8a07",
        "4d2529eb-841c-4cb4-9a60-ebbc15bb507e"
      ],
      "settings": {
        "image": "shopify:\/\/shop_images\/A_tall_highball_glass_filled_halfway_with_the_sap_07ba293b-d9d6-4def-b963-7f205cc0fe5f.png",
        "height": "small",
        "desktop_image_width": "small",
        "layout": "image_first",
        "desktop_content_position": "top",
        "desktop_content_alignment": "left",
        "content_layout": "overlap",
        "color_scheme": "inverse",
        "image_behavior": "ambient",
        "mobile_content_alignment": "left",
        "padding_top": 20,
        "padding_bottom": 0
      }
    },
    "9931fee3-d3bb-4acc-87a4-59d9f59460bd": {
      "type": "featured-blog",
      "settings": {
        "heading": "For The Perfect Drink",
        "heading_size": "h2",
        "blog": "recipes",
        "post_limit": 3,
        "columns_desktop": 3,
        "color_scheme": "scheme-c986199f-beb4-486d-8120-d3e8779b7b9e",
        "show_image": true,
        "show_date": false,
        "show_author": false,
        "show_view_all": false,
        "padding_top": 36,
        "padding_bottom": 36
      }
    },
    "related-products": {
      "type": "related-products",
      "settings": {
        "heading": "The other ones",
        "heading_size": "h2",
        "products_to_show": 4,
        "columns_desktop": 4,
        "color_scheme": "scheme-5f541abf-2222-4580-9242-293f60c35b1b",
        "image_ratio": "portrait",
        "image_shape": "default",
        "show_secondary_image": true,
        "show_vendor": false,
        "show_rating": false,
        "columns_mobile": "2",
        "padding_top": 36,
        "padding_bottom": 36
      }
    }
  },
  "order": [
    "main",
    "4315c828-724c-4210-9c82-6797dbd2bf5d",
    "f22dd3f3-92ca-453d-b11e-673b4447da27",
    "6967ccec-2575-44cc-8175-79ab53e008c4",
    "9931fee3-d3bb-4acc-87a4-59d9f59460bd",
    "related-products"
  ]
}
